wibble/__init__.py
wibble/warble.py
wibble/wobble.py
wibble-0.0.6.dist-info/LICENSE
wibble-0.0.6.dist-info/METADATA
wibble-0.0.6.dist-info/WHEEL
wibble-0.0.6.dist-info/entry_points.txt
wibble-0.0.6.dist-info/RECORD
